academictorrents/Client.py
academictorrents/HttpPeer.py
academictorrents/Peer.py
academictorrents/PeerSeeker.py
academictorrents/PeersManager.py
academictorrents/Piece.py
academictorrents/PiecesManager.py
academictorrents/RarestPieces.py
academictorrents/Torrent.py
academictorrents/Tracker.py
academictorrents/__init__.py
academictorrents/academictorrents.py
academictorrents/progress_bar.py
academictorrents/utils.py
academictorrents/version.py
academictorrents-2.0.21.dist-info/DESCRIPTION.rst
academictorrents-2.0.21.dist-info/METADATA
academictorrents-2.0.21.dist-info/RECORD
academictorrents-2.0.21.dist-info/WHEEL
academictorrents-2.0.21.dist-info/metadata.json
academictorrents-2.0.21.dist-info/top_level.txt
