Metadata-Version: 2.0
Name: academictorrents
Version: 2.0.21
Summary: Academic Torrents Python APIs
Home-page: https://github.com/AcademicTorrents/python-r-api
Author: Martin Weiss, Alexis Gallepe, Jonathan Nogueira
Author-email: contact@academictorrents.com
License: MIT License
Requires-Dist: bencode.py (==2.0.0)
Requires-Dist: bitstring (==3.1.5)
Requires-Dist: PyPubSub (==3.3.0)
Requires-Dist: requests (==2.7.0)
Requires-Dist: future (==0.16.0)
